<?xml version = '1.0' encoding = 'windows-1252'?>
<nfdrs>
   <row num="1">
      <sta_id>44915</sta_id>
      <sta_nm>SAN LUIS OBISPO</sta_nm>
      <latitude>  35.3030</latitude>
      <longitude>-120.6787</longitude>
      <nfdr_dt>07/31/2020</nfdr_dt>
      <nfdr_tm>13</nfdr_tm>
      <nfdr_type>F</nfdr_type>
      <mp>1</mp>
      <msgc>7G1A3</msgc>
      <one_hr>6.46</one_hr>
      <ten_hr>8.29</ten_hr>
      <hu_hr>15.61</hu_hr>
      <th_hr>14.94</th_hr>
      <xh_hr>12.81</xh_hr>
      <ic>26.6</ic>
      <kbdi>494</kbdi>
      <sc>9</sc>
      <ec>39.1</ec>
      <bi>44.6</bi>
      <sl>4 </sl>
      <lr>0</lr>
      <lo>0</lo>
      <hr>0</hr>
      <ho>0</ho>
      <fl>32</fl>
      <hrb>6.5</hrb>
      <wdy>110.5</wdy>
      <herb_gsi>0</herb_gsi>
      <woody_gsi>0</woody_gsi>
      <adj>H </adj>
   </row>
   <row num="2">
      <sta_id>44915</sta_id>
      <sta_nm>SAN LUIS OBISPO</sta_nm>
      <latitude>  35.3030</latitude>
      <longitude>-120.6787</longitude>
      <nfdr_dt>07/31/2020</nfdr_dt>
      <nfdr_tm>13</nfdr_tm>
      <nfdr_type>F</nfdr_type>
      <mp>2</mp>
      <msgc>16V2A </msgc>
      <one_hr>22.7</one_hr>
      <ten_hr>20.27</ten_hr>
      <hu_hr>16.17</hu_hr>
      <th_hr>17.48</th_hr>
      <xh_hr>-99.99</xh_hr>
      <ic>0</ic>
      <kbdi>494</kbdi>
      <sc>0</sc>
      <ec>0</ec>
      <bi>0</bi>
      <lr>0</lr>
      <lo>0</lo>
      <hr>0</hr>
      <ho>0</ho>
      <fl>0</fl>
      <hrb>117</hrb>
      <wdy>171</wdy>
      <herb_gsi>0.9</herb_gsi>
      <woody_gsi>0.9</woody_gsi>
   </row>
   <row num="3">
      <sta_id>44915</sta_id>
      <sta_nm>SAN LUIS OBISPO</sta_nm>
      <latitude>  35.3030</latitude>
      <longitude>-120.6787</longitude>
      <nfdr_dt>07/31/2020</nfdr_dt>
      <nfdr_tm>13</nfdr_tm>
      <nfdr_type>F</nfdr_type>
      <mp>3</mp>
      <msgc>16W2A </msgc>
      <one_hr>22.7</one_hr>
      <ten_hr>20.27</ten_hr>
      <hu_hr>16.17</hu_hr>
      <th_hr>17.48</th_hr>
      <xh_hr>-99.99</xh_hr>
      <ic>0</ic>
      <kbdi>494</kbdi>
      <sc>0</sc>
      <ec>0</ec>
      <bi>0</bi>
      <lr>0</lr>
      <lo>0</lo>
      <hr>0</hr>
      <ho>0</ho>
      <fl>0</fl>
      <hrb>117</hrb>
      <wdy>171</wdy>
      <herb_gsi>0.9</herb_gsi>
      <woody_gsi>0.9</woody_gsi>
   </row>
   <row num="4">
      <sta_id>44915</sta_id>
      <sta_nm>SAN LUIS OBISPO</sta_nm>
      <latitude>  35.3030</latitude>
      <longitude>-120.6787</longitude>
      <nfdr_dt>07/31/2020</nfdr_dt>
      <nfdr_tm>13</nfdr_tm>
      <nfdr_type>F</nfdr_type>
      <mp>4</mp>
      <msgc>16X2A </msgc>
      <one_hr>22.7</one_hr>
      <ten_hr>20.27</ten_hr>
      <hu_hr>16.17</hu_hr>
      <th_hr>17.48</th_hr>
      <xh_hr>-99.99</xh_hr>
      <ic>0.2</ic>
      <kbdi>494</kbdi>
      <sc>6.5</sc>
      <ec>5</ec>
      <bi>14.9</bi>
      <lr>0</lr>
      <lo>0</lo>
      <hr>0</hr>
      <ho>0</ho>
      <fl>11</fl>
      <hrb>117</hrb>
      <wdy>171</wdy>
      <herb_gsi>0.9</herb_gsi>
      <woody_gsi>0.9</woody_gsi>
   </row>
   <row num="5">
      <sta_id>44915</sta_id>
      <sta_nm>SAN LUIS OBISPO</sta_nm>
      <latitude>  35.3030</latitude>
      <longitude>-120.6787</longitude>
      <nfdr_dt>07/31/2020</nfdr_dt>
      <nfdr_tm>13</nfdr_tm>
      <nfdr_type>F</nfdr_type>
      <mp>5</mp>
      <msgc>16Y2A </msgc>
      <one_hr>22.7</one_hr>
      <ten_hr>20.27</ten_hr>
      <hu_hr>16.17</hu_hr>
      <th_hr>17.48</th_hr>
      <xh_hr>-99.99</xh_hr>
      <ic>0.4</ic>
      <kbdi>494</kbdi>
      <sc>1.1</sc>
      <ec>20.1</ec>
      <bi>12.6</bi>
      <lr>0</lr>
      <lo>0</lo>
      <hr>0</hr>
      <ho>0</ho>
      <fl>9</fl>
      <hrb>117</hrb>
      <wdy>171</wdy>
      <herb_gsi>0.9</herb_gsi>
      <woody_gsi>0.9</woody_gsi>
   </row>
   <row num="6">
      <sta_id>44915</sta_id>
      <sta_nm>SAN LUIS OBISPO</sta_nm>
      <latitude>  35.3030</latitude>
      <longitude>-120.6787</longitude>
      <nfdr_dt>07/31/2020</nfdr_dt>
      <nfdr_tm>13</nfdr_tm>
      <nfdr_type>F</nfdr_type>
      <mp>6</mp>
      <msgc>16Z2A </msgc>
      <one_hr>22.7</one_hr>
      <ten_hr>20.27</ten_hr>
      <hu_hr>16.17</hu_hr>
      <th_hr>17.48</th_hr>
      <xh_hr>-99.99</xh_hr>
      <ic>0.4</ic>
      <kbdi>494</kbdi>
      <sc>4.2</sc>
      <ec>30.8</ec>
      <bi>28.1</bi>
      <lr>0</lr>
      <lo>0</lo>
      <hr>0</hr>
      <ho>0</ho>
      <fl>20</fl>
      <hrb>117</hrb>
      <wdy>171</wdy>
      <herb_gsi>0.9</herb_gsi>
      <woody_gsi>0.9</woody_gsi>
   </row>
   <row num="7">
      <sta_id>44915</sta_id>
      <sta_nm>SAN LUIS OBISPO</sta_nm>
      <latitude>  35.3030</latitude>
      <longitude>-120.6787</longitude>
      <nfdr_dt>07/30/2020</nfdr_dt>
      <nfdr_tm>13</nfdr_tm>
      <nfdr_type>F</nfdr_type>
      <mp>1</mp>
      <msgc>7G1A3</msgc>
      <one_hr>6.45</one_hr>
      <ten_hr>8.25</ten_hr>
      <hu_hr>15.45</hu_hr>
      <th_hr>14.88</th_hr>
      <xh_hr>12.77</xh_hr>
      <ic>25.2</ic>
      <kbdi>492</kbdi>
      <sc>7.9</sc>
      <ec>39.5</ec>
      <bi>42.2</bi>
      <sl>4 </sl>
      <lr>0</lr>
      <lo>0</lo>
      <hr>0</hr>
      <ho>0</ho>
      <fl>30</fl>
      <hrb>6.4</hrb>
      <wdy>109.9</wdy>
      <herb_gsi>0</herb_gsi>
      <woody_gsi>0</woody_gsi>
      <adj>H </adj>
   </row>
   <row num="8">
      <sta_id>44915</sta_id>
      <sta_nm>SAN LUIS OBISPO</sta_nm>
      <latitude>  35.3030</latitude>
      <longitude>-120.6787</longitude>
      <nfdr_dt>07/30/2020</nfdr_dt>
      <nfdr_tm>12</nfdr_tm>
      <nfdr_type>O</nfdr_type>
      <mp>1</mp>
      <msgc>7G1A3</msgc>
      <one_hr>9.56</one_hr>
      <ten_hr>10.84</ten_hr>
      <hu_hr>15.99</hu_hr>
      <th_hr>14.95</th_hr>
      <xh_hr>12.82</xh_hr>
      <ic>12.7</ic>
      <kbdi>494</kbdi>
      <sc>6.9</sc>
      <ec>35.8</ec>
      <bi>37.9</bi>
      <sl>1 </sl>
      <lr>0</lr>
      <lo>0</lo>
      <hr>0</hr>
      <ho>0</ho>
      <fl>27</fl>
      <hrb>9.6</hrb>
      <wdy>110.6</wdy>
      <herb_gsi>0</herb_gsi>
      <woody_gsi>0</woody_gsi>
      <adj>L </adj>
   </row>
   <row num="9">
      <sta_id>44915</sta_id>
      <sta_nm>SAN LUIS OBISPO</sta_nm>
      <latitude>  35.3030</latitude>
      <longitude>-120.6787</longitude>
      <nfdr_dt>07/30/2020</nfdr_dt>
      <nfdr_tm>14</nfdr_tm>
      <nfdr_type>S</nfdr_type>
      <mp>1</mp>
      <msgc>7G1A3</msgc>
      <one_hr>8.62</one_hr>
      <ten_hr>10.05</ten_hr>
      <hu_hr>15.77</hu_hr>
      <th_hr>14.9</th_hr>
      <xh_hr>12.79</xh_hr>
      <ic>16.7</ic>
      <kbdi>492</kbdi>
      <sc>8.1</sc>
      <ec>37</ec>
      <bi>41.5</bi>
      <sl>4 </sl>
      <lr>0</lr>
      <lo>0</lo>
      <hr>0</hr>
      <ho>0</ho>
      <fl>29</fl>
      <hrb>7.1</hrb>
      <wdy>110.1</wdy>
      <herb_gsi>0</herb_gsi>
      <woody_gsi>0</woody_gsi>
      <adj>M </adj>
   </row>
   <row num="10">
      <sta_id>44915</sta_id>
      <sta_nm>SAN LUIS OBISPO</sta_nm>
      <latitude>  35.3030</latitude>
      <longitude>-120.6787</longitude>
      <nfdr_dt>07/30/2020</nfdr_dt>
      <nfdr_tm>16</nfdr_tm>
      <nfdr_type>S</nfdr_type>
      <mp>1</mp>
      <msgc>7G1A3</msgc>
      <one_hr>11.93</one_hr>
      <ten_hr>12.7</ten_hr>
      <hu_hr>15.77</hu_hr>
      <th_hr>14.9</th_hr>
      <xh_hr>12.79</xh_hr>
      <ic>7.5</ic>
      <kbdi>492</kbdi>
      <sc>7.3</sc>
      <ec>34.1</ec>
      <bi>38</bi>
      <sl>4 </sl>
      <lr>0</lr>
      <lo>0</lo>
      <hr>0</hr>
      <ho>0</ho>
      <fl>27</fl>
      <hrb>7.1</hrb>
      <wdy>110.1</wdy>
      <herb_gsi>0</herb_gsi>
      <woody_gsi>0</woody_gsi>
      <adj>M </adj>
   </row>
   <row num="11">
      <sta_id>44915</sta_id>
      <sta_nm>SAN LUIS OBISPO</sta_nm>
      <latitude>  35.3030</latitude>
      <longitude>-120.6787</longitude>
      <nfdr_dt>07/30/2020</nfdr_dt>
      <nfdr_tm>8</nfdr_tm>
      <nfdr_type>S</nfdr_type>
      <mp>1</mp>
      <msgc>7G1A3</msgc>
      <one_hr>23.18</one_hr>
      <ten_hr>21.7</ten_hr>
      <hu_hr>15.77</hu_hr>
      <th_hr>14.9</th_hr>
      <xh_hr>12.79</xh_hr>
      <ic>0</ic>
      <kbdi>492</kbdi>
      <sc>1.4</sc>
      <ec>24.8</ec>
      <bi>15.6</bi>
      <sl>1 </sl>
      <lr>0</lr>
      <lo>0</lo>
      <hr>0</hr>
      <ho>0</ho>
      <fl>11</fl>
      <hrb>7.1</hrb>
      <wdy>110.1</wdy>
      <herb_gsi>0</herb_gsi>
      <woody_gsi>0</woody_gsi>
      <adj>L </adj>
   </row>
   <row num="12">
      <sta_id>44915</sta_id>
      <sta_nm>SAN LUIS OBISPO</sta_nm>
      <latitude>  35.3030</latitude>
      <longitude>-120.6787</longitude>
      <nfdr_dt>07/30/2020</nfdr_dt>
      <nfdr_tm>13</nfdr_tm>
      <nfdr_type>F</nfdr_type>
      <mp>2</mp>
      <msgc>16V2A </msgc>
      <one_hr>20.87</one_hr>
      <ten_hr>20.9</ten_hr>
      <hu_hr>16.11</hu_hr>
      <th_hr>17.47</th_hr>
      <xh_hr>-99.99</xh_hr>
      <ic>0</ic>
      <kbdi>492</kbdi>
      <sc>0</sc>
      <ec>0</ec>
      <bi>0</bi>
      <lr>0</lr>
      <lo>0</lo>
      <hr>0</hr>
      <ho>0</ho>
      <fl>0</fl>
      <hrb>117</hrb>
      <wdy>170</wdy>
      <herb_gsi>0.89</herb_gsi>
      <woody_gsi>0.89</woody_gsi>
   </row>
   <row num="13">
      <sta_id>44915</sta_id>
      <sta_nm>SAN LUIS OBISPO</sta_nm>
      <latitude>  35.3030</latitude>
      <longitude>-120.6787</longitude>
      <nfdr_dt>07/30/2020</nfdr_dt>
      <nfdr_tm>12</nfdr_tm>
      <nfdr_type>N</nfdr_type>
      <mp>2</mp>
      <msgc>16V2A </msgc>
      <one_hr>14.02</one_hr>
      <ten_hr>17.43</ten_hr>
      <hu_hr>16.59</hu_hr>
      <th_hr>17.47</th_hr>
      <xh_hr>-99.99</xh_hr>
      <ic>0.4</ic>
      <kbdi>494</kbdi>
      <sc>0.2</sc>
      <ec>0</ec>
      <bi>0.2</bi>
      <lr>0</lr>
      <lo>0</lo>
      <hr>0</hr>
      <ho>0</ho>
      <fl>0</fl>
      <hrb>117</hrb>
      <wdy>183</wdy>
      <herb_gsi>0.94</herb_gsi>
      <woody_gsi>0.94</woody_gsi>
   </row>
   <row num="14">
      <sta_id>44915</sta_id>
      <sta_nm>SAN LUIS OBISPO</sta_nm>
      <latitude>  35.3030</latitude>
      <longitude>-120.6787</longitude>
      <nfdr_dt>07/30/2020</nfdr_dt>
      <nfdr_tm>13</nfdr_tm>
      <nfdr_type>F</nfdr_type>
      <mp>3</mp>
      <msgc>16W2A </msgc>
      <one_hr>20.87</one_hr>
      <ten_hr>20.9</ten_hr>
      <hu_hr>16.11</hu_hr>
      <th_hr>17.47</th_hr>
      <xh_hr>-99.99</xh_hr>
      <ic>0</ic>
      <kbdi>492</kbdi>
      <sc>0</sc>
      <ec>0</ec>
      <bi>0</bi>
      <lr>0</lr>
      <lo>0</lo>
      <hr>0</hr>
      <ho>0</ho>
      <fl>0</fl>
      <hrb>117</hrb>
      <wdy>170</wdy>
      <herb_gsi>0.89</herb_gsi>
      <woody_gsi>0.89</woody_gsi>
   </row>
   <row num="15">
      <sta_id>44915</sta_id>
      <sta_nm>SAN LUIS OBISPO</sta_nm>
      <latitude>  35.3030</latitude>
      <longitude>-120.6787</longitude>
      <nfdr_dt>07/30/2020</nfdr_dt>
      <nfdr_tm>12</nfdr_tm>
      <nfdr_type>N</nfdr_type>
      <mp>3</mp>
      <msgc>16W2A </msgc>
      <one_hr>14.02</one_hr>
      <ten_hr>17.43</ten_hr>
      <hu_hr>16.59</hu_hr>
      <th_hr>17.47</th_hr>
      <xh_hr>-99.99</xh_hr>
      <ic>1.2</ic>
      <kbdi>494</kbdi>
      <sc>0.8</sc>
      <ec>0</ec>
      <bi>0</bi>
      <lr>0</lr>
      <lo>0</lo>
      <hr>0</hr>
      <ho>0</ho>
      <fl>0</fl>
      <hrb>117</hrb>
      <wdy>183</wdy>
      <herb_gsi>0.94</herb_gsi>
      <woody_gsi>0.94</woody_gsi>
   </row>
   <row num="16">
      <sta_id>44915</sta_id>
      <sta_nm>SAN LUIS OBISPO</sta_nm>
      <latitude>  35.3030</latitude>
      <longitude>-120.6787</longitude>
      <nfdr_dt>07/30/2020</nfdr_dt>
      <nfdr_tm>13</nfdr_tm>
      <nfdr_type>F</nfdr_type>
      <mp>4</mp>
      <msgc>16X2A </msgc>
      <one_hr>20.87</one_hr>
      <ten_hr>20.9</ten_hr>
      <hu_hr>16.11</hu_hr>
      <th_hr>17.47</th_hr>
      <xh_hr>-99.99</xh_hr>
      <ic>0.6</ic>
      <kbdi>492</kbdi>
      <sc>8.9</sc>
      <ec>6.7</ec>
      <bi>19.6</bi>
      <lr>0</lr>
      <lo>0</lo>
      <hr>0</hr>
      <ho>0</ho>
      <fl>14</fl>
      <hrb>117</hrb>
      <wdy>170</wdy>
      <herb_gsi>0.89</herb_gsi>
      <woody_gsi>0.89</woody_gsi>
   </row>
   <row num="17">
      <sta_id>44915</sta_id>
      <sta_nm>SAN LUIS OBISPO</sta_nm>
      <latitude>  35.3030</latitude>
      <longitude>-120.6787</longitude>
      <nfdr_dt>07/30/2020</nfdr_dt>
      <nfdr_tm>12</nfdr_tm>
      <nfdr_type>N</nfdr_type>
      <mp>4</mp>
      <msgc>16X2A </msgc>
      <one_hr>14.02</one_hr>
      <ten_hr>17.43</ten_hr>
      <hu_hr>16.59</hu_hr>
      <th_hr>17.47</th_hr>
      <xh_hr>-99.99</xh_hr>
      <ic>3.5</ic>
      <kbdi>494</kbdi>
      <sc>12.7</sc>
      <ec>17.2</ec>
      <bi>35.9</bi>
      <lr>0</lr>
      <lo>0</lo>
      <hr>0</hr>
      <ho>0</ho>
      <fl>25</fl>
      <hrb>117</hrb>
      <wdy>183</wdy>
      <herb_gsi>0.94</herb_gsi>
      <woody_gsi>0.94</woody_gsi>
   </row>
   <row num="18">
      <sta_id>44915</sta_id>
      <sta_nm>SAN LUIS OBISPO</sta_nm>
      <latitude>  35.3030</latitude>
      <longitude>-120.6787</longitude>
      <nfdr_dt>07/30/2020</nfdr_dt>
      <nfdr_tm>13</nfdr_tm>
      <nfdr_type>F</nfdr_type>
      <mp>5</mp>
      <msgc>16Y2A </msgc>
      <one_hr>20.87</one_hr>
      <ten_hr>20.9</ten_hr>
      <hu_hr>16.11</hu_hr>
      <th_hr>17.47</th_hr>
      <xh_hr>-99.99</xh_hr>
      <ic>1.1</ic>
      <kbdi>492</kbdi>
      <sc>1.6</sc>
      <ec>20.7</ec>
      <bi>15</bi>
      <lr>0</lr>
      <lo>0</lo>
      <hr>0</hr>
      <ho>0</ho>
      <fl>11</fl>
      <hrb>117</hrb>
      <wdy>170</wdy>
      <herb_gsi>0.89</herb_gsi>
      <woody_gsi>0.89</woody_gsi>
   </row>
   <row num="19">
      <sta_id>44915</sta_id>
      <sta_nm>SAN LUIS OBISPO</sta_nm>
      <latitude>  35.3030</latitude>
      <longitude>-120.6787</longitude>
      <nfdr_dt>07/30/2020</nfdr_dt>
      <nfdr_tm>12</nfdr_tm>
      <nfdr_type>N</nfdr_type>
      <mp>5</mp>
      <msgc>16Y2A </msgc>
      <one_hr>14.02</one_hr>
      <ten_hr>17.43</ten_hr>
      <hu_hr>16.59</hu_hr>
      <th_hr>17.47</th_hr>
      <xh_hr>-99.99</xh_hr>
      <ic>7.4</ic>
      <kbdi>494</kbdi>
      <sc>2.8</sc>
      <ec>25.1</ec>
      <bi>21.3</bi>
      <lr>0</lr>
      <lo>0</lo>
      <hr>0</hr>
      <ho>0</ho>
      <fl>15</fl>
      <hrb>117</hrb>
      <wdy>183</wdy>
      <herb_gsi>0.94</herb_gsi>
      <woody_gsi>0.94</woody_gsi>
   </row>
   <row num="20">
      <sta_id>44915</sta_id>
      <sta_nm>SAN LUIS OBISPO</sta_nm>
      <latitude>  35.3030</latitude>
      <longitude>-120.6787</longitude>
      <nfdr_dt>07/30/2020</nfdr_dt>
      <nfdr_tm>13</nfdr_tm>
      <nfdr_type>F</nfdr_type>
      <mp>6</mp>
      <msgc>16Z2A </msgc>
      <one_hr>20.87</one_hr>
      <ten_hr>20.9</ten_hr>
      <hu_hr>16.11</hu_hr>
      <th_hr>17.47</th_hr>
      <xh_hr>-99.99</xh_hr>
      <ic>1.1</ic>
      <kbdi>492</kbdi>
      <sc>5.7</sc>
      <ec>32.9</ec>
      <bi>33.4</bi>
      <lr>0</lr>
      <lo>0</lo>
      <hr>0</hr>
      <ho>0</ho>
      <fl>24</fl>
      <hrb>117</hrb>
      <wdy>170</wdy>
      <herb_gsi>0.89</herb_gsi>
      <woody_gsi>0.89</woody_gsi>
   </row>
   <row num="21">
      <sta_id>44915</sta_id>
      <sta_nm>SAN LUIS OBISPO</sta_nm>
      <latitude>  35.3030</latitude>
      <longitude>-120.6787</longitude>
      <nfdr_dt>07/30/2020</nfdr_dt>
      <nfdr_tm>12</nfdr_tm>
      <nfdr_type>N</nfdr_type>
      <mp>6</mp>
      <msgc>16Z2A </msgc>
      <one_hr>14.02</one_hr>
      <ten_hr>17.43</ten_hr>
      <hu_hr>16.59</hu_hr>
      <th_hr>17.47</th_hr>
      <xh_hr>-99.99</xh_hr>
      <ic>7.3</ic>
      <kbdi>494</kbdi>
      <sc>10.1</sc>
      <ec>49.8</ec>
      <bi>52.7</bi>
      <lr>0</lr>
      <lo>0</lo>
      <hr>0</hr>
      <ho>0</ho>
      <fl>37</fl>
      <hrb>117</hrb>
      <wdy>183</wdy>
      <herb_gsi>0.94</herb_gsi>
      <woody_gsi>0.94</woody_gsi>
   </row>
</nfdrs>
