<?xml version = '1.0' encoding = 'windows-1252'?>
<nfdrs>
   <row num="1">
      <sta_id>44904</sta_id>
      <sta_nm>LAS TABLAS</sta_nm>
      <latitude>  35.6564</latitude>
      <longitude>-120.9241</longitude>
      <nfdr_dt>07/06/2020</nfdr_dt>
      <nfdr_tm>13</nfdr_tm>
      <nfdr_type>F</nfdr_type>
      <mp>1</mp>
      <msgc>7G2A2</msgc>
      <one_hr>2</one_hr>
      <ten_hr>3</ten_hr>
      <hu_hr>9</hu_hr>
      <th_hr>12</th_hr>
      <xh_hr>10</xh_hr>
      <ic>51</ic>
      <kbdi>463</kbdi>
      <sc>7.8</sc>
      <ec>61.2</ec>
      <bi>51.4</bi>
      <sl>4 </sl>
      <lr>0</lr>
      <lo>0</lo>
      <hr>0</hr>
      <ho>0</ho>
      <fl>36</fl>
      <hrb>2</hrb>
      <wdy>92.8</wdy>
      <herb_gsi>0</herb_gsi>
      <woody_gsi>0</woody_gsi>
      <adj>V </adj>
   </row>
   <row num="2">
      <sta_id>44904</sta_id>
      <sta_nm>LAS TABLAS</sta_nm>
      <latitude>  35.6564</latitude>
      <longitude>-120.9241</longitude>
      <nfdr_dt>07/06/2020</nfdr_dt>
      <nfdr_tm>13</nfdr_tm>
      <nfdr_type>F</nfdr_type>
      <mp>2</mp>
      <msgc>16V2A </msgc>
      <one_hr>10.22</one_hr>
      <ten_hr>6.79</ten_hr>
      <hu_hr>12</hu_hr>
      <th_hr>15</th_hr>
      <xh_hr>-100</xh_hr>
      <ic>10.4</ic>
      <kbdi>463</kbdi>
      <sc>14.3</sc>
      <ec>1.5</ec>
      <bi>12.3</bi>
      <lr>0</lr>
      <lo>0</lo>
      <hr>0</hr>
      <ho>0</ho>
      <fl>9</fl>
      <hrb>53</hrb>
      <wdy>138</wdy>
      <herb_gsi>0.78</herb_gsi>
      <woody_gsi>0.78</woody_gsi>
   </row>
   <row num="3">
      <sta_id>44904</sta_id>
      <sta_nm>LAS TABLAS</sta_nm>
      <latitude>  35.6564</latitude>
      <longitude>-120.9241</longitude>
      <nfdr_dt>07/06/2020</nfdr_dt>
      <nfdr_tm>13</nfdr_tm>
      <nfdr_type>F</nfdr_type>
      <mp>3</mp>
      <msgc>16W2A </msgc>
      <one_hr>10.22</one_hr>
      <ten_hr>6.79</ten_hr>
      <hu_hr>12</hu_hr>
      <th_hr>15</th_hr>
      <xh_hr>-100</xh_hr>
      <ic>6.9</ic>
      <kbdi>463</kbdi>
      <sc>3.6</sc>
      <ec>3.5</ec>
      <bi>9.7</bi>
      <lr>0</lr>
      <lo>0</lo>
      <hr>0</hr>
      <ho>0</ho>
      <fl>7</fl>
      <hrb>53</hrb>
      <wdy>138</wdy>
      <herb_gsi>0.78</herb_gsi>
      <woody_gsi>0.78</woody_gsi>
   </row>
   <row num="4">
      <sta_id>44904</sta_id>
      <sta_nm>LAS TABLAS</sta_nm>
      <latitude>  35.6564</latitude>
      <longitude>-120.9241</longitude>
      <nfdr_dt>07/06/2020</nfdr_dt>
      <nfdr_tm>13</nfdr_tm>
      <nfdr_type>F</nfdr_type>
      <mp>4</mp>
      <msgc>16X2A </msgc>
      <one_hr>10.22</one_hr>
      <ten_hr>6.79</ten_hr>
      <hu_hr>12</hu_hr>
      <th_hr>15</th_hr>
      <xh_hr>-100</xh_hr>
      <ic>13.3</ic>
      <kbdi>463</kbdi>
      <sc>22.8</sc>
      <ec>47</ec>
      <bi>74.5</bi>
      <lr>0</lr>
      <lo>0</lo>
      <hr>0</hr>
      <ho>0</ho>
      <fl>53</fl>
      <hrb>53</hrb>
      <wdy>138</wdy>
      <herb_gsi>0.78</herb_gsi>
      <woody_gsi>0.78</woody_gsi>
   </row>
   <row num="5">
      <sta_id>44904</sta_id>
      <sta_nm>LAS TABLAS</sta_nm>
      <latitude>  35.6564</latitude>
      <longitude>-120.9241</longitude>
      <nfdr_dt>07/06/2020</nfdr_dt>
      <nfdr_tm>13</nfdr_tm>
      <nfdr_type>F</nfdr_type>
      <mp>5</mp>
      <msgc>16Y2A </msgc>
      <one_hr>10.22</one_hr>
      <ten_hr>6.79</ten_hr>
      <hu_hr>12</hu_hr>
      <th_hr>15</th_hr>
      <xh_hr>-100</xh_hr>
      <ic>19.9</ic>
      <kbdi>463</kbdi>
      <sc>2.4</sc>
      <ec>41.6</ec>
      <bi>25.2</bi>
      <lr>0</lr>
      <lo>0</lo>
      <hr>0</hr>
      <ho>0</ho>
      <fl>18</fl>
      <hrb>53</hrb>
      <wdy>138</wdy>
      <herb_gsi>0.78</herb_gsi>
      <woody_gsi>0.78</woody_gsi>
   </row>
   <row num="6">
      <sta_id>44904</sta_id>
      <sta_nm>LAS TABLAS</sta_nm>
      <latitude>  35.6564</latitude>
      <longitude>-120.9241</longitude>
      <nfdr_dt>07/06/2020</nfdr_dt>
      <nfdr_tm>13</nfdr_tm>
      <nfdr_type>F</nfdr_type>
      <mp>6</mp>
      <msgc>16Z2A </msgc>
      <one_hr>10.22</one_hr>
      <ten_hr>6.79</ten_hr>
      <hu_hr>12</hu_hr>
      <th_hr>15</th_hr>
      <xh_hr>-100</xh_hr>
      <ic>17.1</ic>
      <kbdi>463</kbdi>
      <sc>6.8</sc>
      <ec>93.5</ec>
      <bi>58.8</bi>
      <lr>0</lr>
      <lo>0</lo>
      <hr>0</hr>
      <ho>0</ho>
      <fl>42</fl>
      <hrb>53</hrb>
      <wdy>138</wdy>
      <herb_gsi>0.78</herb_gsi>
      <woody_gsi>0.78</woody_gsi>
   </row>
   <row num="7">
      <sta_id>44904</sta_id>
      <sta_nm>LAS TABLAS</sta_nm>
      <latitude>  35.6564</latitude>
      <longitude>-120.9241</longitude>
      <nfdr_dt>07/05/2020</nfdr_dt>
      <nfdr_tm>13</nfdr_tm>
      <nfdr_type>F</nfdr_type>
      <mp>1</mp>
      <msgc>7G2A2</msgc>
      <one_hr>2</one_hr>
      <ten_hr>3</ten_hr>
      <hu_hr>10</hu_hr>
      <th_hr>12</th_hr>
      <xh_hr>11</xh_hr>
      <ic>47.1</ic>
      <kbdi>456</kbdi>
      <sc>6.7</sc>
      <ec>59.4</ec>
      <bi>47.1</bi>
      <sl>4 </sl>
      <lr>0</lr>
      <lo>0</lo>
      <hr>0</hr>
      <ho>0</ho>
      <fl>33</fl>
      <hrb>2</hrb>
      <wdy>95.3</wdy>
      <herb_gsi>0</herb_gsi>
      <woody_gsi>0</woody_gsi>
      <adj>V </adj>
   </row>
   <row num="8">
      <sta_id>44904</sta_id>
      <sta_nm>LAS TABLAS</sta_nm>
      <latitude>  35.6564</latitude>
      <longitude>-120.9241</longitude>
      <nfdr_dt>07/05/2020</nfdr_dt>
      <nfdr_tm>13</nfdr_tm>
      <nfdr_type>O</nfdr_type>
      <mp>1</mp>
      <msgc>7G2A2</msgc>
      <one_hr>2</one_hr>
      <ten_hr>3.2</ten_hr>
      <hu_hr>10</hu_hr>
      <th_hr>12</th_hr>
      <xh_hr>11</xh_hr>
      <ic>47.1</ic>
      <kbdi>463</kbdi>
      <sc>6.6</sc>
      <ec>58.9</ec>
      <bi>46.9</bi>
      <sl>4 </sl>
      <lr>0</lr>
      <lo>0</lo>
      <hr>0</hr>
      <ho>0</ho>
      <fl>33</fl>
      <hrb>2</hrb>
      <wdy>95.5</wdy>
      <herb_gsi>0</herb_gsi>
      <woody_gsi>0</woody_gsi>
      <adj>V </adj>
   </row>
   <row num="9">
      <sta_id>44904</sta_id>
      <sta_nm>LAS TABLAS</sta_nm>
      <latitude>  35.6564</latitude>
      <longitude>-120.9241</longitude>
      <nfdr_dt>07/05/2020</nfdr_dt>
      <nfdr_tm>15</nfdr_tm>
      <nfdr_type>S</nfdr_type>
      <mp>1</mp>
      <msgc>7G2A2</msgc>
      <one_hr>2</one_hr>
      <ten_hr>3.66</ten_hr>
      <hu_hr>11</hu_hr>
      <th_hr>12</th_hr>
      <xh_hr>11</xh_hr>
      <ic>50.5</ic>
      <kbdi>456</kbdi>
      <sc>7.6</sc>
      <ec>56.6</ec>
      <bi>49.1</bi>
      <sl>4 </sl>
      <lr>0</lr>
      <lo>0</lo>
      <hr>0</hr>
      <ho>0</ho>
      <fl>35</fl>
      <hrb>2</hrb>
      <wdy>97.3</wdy>
      <herb_gsi>0</herb_gsi>
      <woody_gsi>0</woody_gsi>
      <adj>V </adj>
   </row>
   <row num="10">
      <sta_id>44904</sta_id>
      <sta_nm>LAS TABLAS</sta_nm>
      <latitude>  35.6564</latitude>
      <longitude>-120.9241</longitude>
      <nfdr_dt>07/05/2020</nfdr_dt>
      <nfdr_tm>9</nfdr_tm>
      <nfdr_type>S</nfdr_type>
      <mp>1</mp>
      <msgc>7G2A2</msgc>
      <one_hr>3.06</one_hr>
      <ten_hr>4.66</ten_hr>
      <hu_hr>11</hu_hr>
      <th_hr>12</th_hr>
      <xh_hr>11</xh_hr>
      <ic>31.2</ic>
      <kbdi>456</kbdi>
      <sc>4.1</sc>
      <ec>55.3</ec>
      <bi>36.6</bi>
      <sl>4 </sl>
      <lr>0</lr>
      <lo>0</lo>
      <hr>0</hr>
      <ho>0</ho>
      <fl>26</fl>
      <hrb>2</hrb>
      <wdy>97.3</wdy>
      <herb_gsi>0</herb_gsi>
      <woody_gsi>0</woody_gsi>
      <adj>H </adj>
   </row>
   <row num="11">
      <sta_id>44904</sta_id>
      <sta_nm>LAS TABLAS</sta_nm>
      <latitude>  35.6564</latitude>
      <longitude>-120.9241</longitude>
      <nfdr_dt>07/05/2020</nfdr_dt>
      <nfdr_tm>17</nfdr_tm>
      <nfdr_type>S</nfdr_type>
      <mp>1</mp>
      <msgc>7G2A2</msgc>
      <one_hr>2</one_hr>
      <ten_hr>3.79</ten_hr>
      <hu_hr>11</hu_hr>
      <th_hr>12</th_hr>
      <xh_hr>11</xh_hr>
      <ic>46.8</ic>
      <kbdi>456</kbdi>
      <sc>6.6</sc>
      <ec>56.5</ec>
      <bi>45.8</bi>
      <sl>4 </sl>
      <lr>0</lr>
      <lo>0</lo>
      <hr>0</hr>
      <ho>0</ho>
      <fl>32</fl>
      <hrb>2</hrb>
      <wdy>97.3</wdy>
      <herb_gsi>0</herb_gsi>
      <woody_gsi>0</woody_gsi>
      <adj>V </adj>
   </row>
   <row num="12">
      <sta_id>44904</sta_id>
      <sta_nm>LAS TABLAS</sta_nm>
      <latitude>  35.6564</latitude>
      <longitude>-120.9241</longitude>
      <nfdr_dt>07/05/2020</nfdr_dt>
      <nfdr_tm>13</nfdr_tm>
      <nfdr_type>F</nfdr_type>
      <mp>2</mp>
      <msgc>16V2A </msgc>
      <one_hr>9.87</one_hr>
      <ten_hr>8.36</ten_hr>
      <hu_hr>14</hu_hr>
      <th_hr>15</th_hr>
      <xh_hr>-100</xh_hr>
      <ic>9.6</ic>
      <kbdi>456</kbdi>
      <sc>10.9</sc>
      <ec>1.5</ec>
      <bi>10.8</bi>
      <lr>0</lr>
      <lo>0</lo>
      <hr>0</hr>
      <ho>0</ho>
      <fl>8</fl>
      <hrb>53</hrb>
      <wdy>142</wdy>
      <herb_gsi>0.79</herb_gsi>
      <woody_gsi>0.79</woody_gsi>
   </row>
   <row num="13">
      <sta_id>44904</sta_id>
      <sta_nm>LAS TABLAS</sta_nm>
      <latitude>  35.6564</latitude>
      <longitude>-120.9241</longitude>
      <nfdr_dt>07/05/2020</nfdr_dt>
      <nfdr_tm>13</nfdr_tm>
      <nfdr_type>N</nfdr_type>
      <mp>2</mp>
      <msgc>16V2A </msgc>
      <one_hr>3.92</one_hr>
      <ten_hr>9.16</ten_hr>
      <hu_hr>12</hu_hr>
      <th_hr>15</th_hr>
      <xh_hr>-100</xh_hr>
      <ic>24.5</ic>
      <kbdi>456</kbdi>
      <sc>12.9</sc>
      <ec>4</ec>
      <bi>18.5</bi>
      <lr>0</lr>
      <lo>0</lo>
      <hr>0</hr>
      <ho>0</ho>
      <fl>13</fl>
      <hrb>53</hrb>
      <wdy>149</wdy>
      <herb_gsi>0.82</herb_gsi>
      <woody_gsi>0.82</woody_gsi>
   </row>
   <row num="14">
      <sta_id>44904</sta_id>
      <sta_nm>LAS TABLAS</sta_nm>
      <latitude>  35.6564</latitude>
      <longitude>-120.9241</longitude>
      <nfdr_dt>07/05/2020</nfdr_dt>
      <nfdr_tm>13</nfdr_tm>
      <nfdr_type>F</nfdr_type>
      <mp>3</mp>
      <msgc>16W2A </msgc>
      <one_hr>9.87</one_hr>
      <ten_hr>8.36</ten_hr>
      <hu_hr>14</hu_hr>
      <th_hr>15</th_hr>
      <xh_hr>-100</xh_hr>
      <ic>6.6</ic>
      <kbdi>456</kbdi>
      <sc>3</sc>
      <ec>3.1</ec>
      <bi>8.3</bi>
      <lr>0</lr>
      <lo>0</lo>
      <hr>0</hr>
      <ho>0</ho>
      <fl>6</fl>
      <hrb>53</hrb>
      <wdy>142</wdy>
      <herb_gsi>0.79</herb_gsi>
      <woody_gsi>0.79</woody_gsi>
   </row>
   <row num="15">
      <sta_id>44904</sta_id>
      <sta_nm>LAS TABLAS</sta_nm>
      <latitude>  35.6564</latitude>
      <longitude>-120.9241</longitude>
      <nfdr_dt>07/05/2020</nfdr_dt>
      <nfdr_tm>13</nfdr_tm>
      <nfdr_type>N</nfdr_type>
      <mp>3</mp>
      <msgc>16W2A </msgc>
      <one_hr>3.92</one_hr>
      <ten_hr>9.16</ten_hr>
      <hu_hr>12</hu_hr>
      <th_hr>15</th_hr>
      <xh_hr>-100</xh_hr>
      <ic>24.9</ic>
      <kbdi>456</kbdi>
      <sc>7.6</sc>
      <ec>7.1</ec>
      <bi>18.9</bi>
      <lr>0</lr>
      <lo>0</lo>
      <hr>0</hr>
      <ho>0</ho>
      <fl>13</fl>
      <hrb>53</hrb>
      <wdy>149</wdy>
      <herb_gsi>0.82</herb_gsi>
      <woody_gsi>0.82</woody_gsi>
   </row>
   <row num="16">
      <sta_id>44904</sta_id>
      <sta_nm>LAS TABLAS</sta_nm>
      <latitude>  35.6564</latitude>
      <longitude>-120.9241</longitude>
      <nfdr_dt>07/05/2020</nfdr_dt>
      <nfdr_tm>13</nfdr_tm>
      <nfdr_type>F</nfdr_type>
      <mp>4</mp>
      <msgc>16X2A </msgc>
      <one_hr>9.87</one_hr>
      <ten_hr>8.36</ten_hr>
      <hu_hr>14</hu_hr>
      <th_hr>15</th_hr>
      <xh_hr>-100</xh_hr>
      <ic>12.8</ic>
      <kbdi>456</kbdi>
      <sc>18.5</sc>
      <ec>44.6</ec>
      <bi>66.1</bi>
      <lr>0</lr>
      <lo>0</lo>
      <hr>0</hr>
      <ho>0</ho>
      <fl>47</fl>
      <hrb>53</hrb>
      <wdy>142</wdy>
      <herb_gsi>0.79</herb_gsi>
      <woody_gsi>0.79</woody_gsi>
   </row>
   <row num="17">
      <sta_id>44904</sta_id>
      <sta_nm>LAS TABLAS</sta_nm>
      <latitude>  35.6564</latitude>
      <longitude>-120.9241</longitude>
      <nfdr_dt>07/05/2020</nfdr_dt>
      <nfdr_tm>13</nfdr_tm>
      <nfdr_type>N</nfdr_type>
      <mp>4</mp>
      <msgc>16X2A </msgc>
      <one_hr>3.92</one_hr>
      <ten_hr>9.16</ten_hr>
      <hu_hr>12</hu_hr>
      <th_hr>15</th_hr>
      <xh_hr>-100</xh_hr>
      <ic>32.8</ic>
      <kbdi>456</kbdi>
      <sc>22.2</sc>
      <ec>66.6</ec>
      <bi>86.4</bi>
      <lr>0</lr>
      <lo>0</lo>
      <hr>0</hr>
      <ho>0</ho>
      <fl>61</fl>
      <hrb>53</hrb>
      <wdy>149</wdy>
      <herb_gsi>0.82</herb_gsi>
      <woody_gsi>0.82</woody_gsi>
   </row>
   <row num="18">
      <sta_id>44904</sta_id>
      <sta_nm>LAS TABLAS</sta_nm>
      <latitude>  35.6564</latitude>
      <longitude>-120.9241</longitude>
      <nfdr_dt>07/05/2020</nfdr_dt>
      <nfdr_tm>13</nfdr_tm>
      <nfdr_type>F</nfdr_type>
      <mp>5</mp>
      <msgc>16Y2A </msgc>
      <one_hr>9.87</one_hr>
      <ten_hr>8.36</ten_hr>
      <hu_hr>14</hu_hr>
      <th_hr>15</th_hr>
      <xh_hr>-100</xh_hr>
      <ic>20.5</ic>
      <kbdi>456</kbdi>
      <sc>2.3</sc>
      <ec>38.3</ec>
      <bi>23.6</bi>
      <lr>0</lr>
      <lo>0</lo>
      <hr>0</hr>
      <ho>0</ho>
      <fl>17</fl>
      <hrb>53</hrb>
      <wdy>142</wdy>
      <herb_gsi>0.79</herb_gsi>
      <woody_gsi>0.79</woody_gsi>
   </row>
   <row num="19">
      <sta_id>44904</sta_id>
      <sta_nm>LAS TABLAS</sta_nm>
      <latitude>  35.6564</latitude>
      <longitude>-120.9241</longitude>
      <nfdr_dt>07/05/2020</nfdr_dt>
      <nfdr_tm>13</nfdr_tm>
      <nfdr_type>N</nfdr_type>
      <mp>5</mp>
      <msgc>16Y2A </msgc>
      <one_hr>3.92</one_hr>
      <ten_hr>9.16</ten_hr>
      <hu_hr>12</hu_hr>
      <th_hr>15</th_hr>
      <xh_hr>-100</xh_hr>
      <ic>59.1</ic>
      <kbdi>456</kbdi>
      <sc>3.5</sc>
      <ec>44.7</ec>
      <bi>30.6</bi>
      <lr>0</lr>
      <lo>0</lo>
      <hr>0</hr>
      <ho>0</ho>
      <fl>22</fl>
      <hrb>53</hrb>
      <wdy>149</wdy>
      <herb_gsi>0.82</herb_gsi>
      <woody_gsi>0.82</woody_gsi>
   </row>
   <row num="20">
      <sta_id>44904</sta_id>
      <sta_nm>LAS TABLAS</sta_nm>
      <latitude>  35.6564</latitude>
      <longitude>-120.9241</longitude>
      <nfdr_dt>07/05/2020</nfdr_dt>
      <nfdr_tm>13</nfdr_tm>
      <nfdr_type>F</nfdr_type>
      <mp>6</mp>
      <msgc>16Z2A </msgc>
      <one_hr>9.87</one_hr>
      <ten_hr>8.36</ten_hr>
      <hu_hr>14</hu_hr>
      <th_hr>15</th_hr>
      <xh_hr>-100</xh_hr>
      <ic>16.9</ic>
      <kbdi>456</kbdi>
      <sc>6</sc>
      <ec>85</ec>
      <bi>52.9</bi>
      <lr>0</lr>
      <lo>0</lo>
      <hr>0</hr>
      <ho>0</ho>
      <fl>37</fl>
      <hrb>53</hrb>
      <wdy>142</wdy>
      <herb_gsi>0.79</herb_gsi>
      <woody_gsi>0.79</woody_gsi>
   </row>
   <row num="21">
      <sta_id>44904</sta_id>
      <sta_nm>LAS TABLAS</sta_nm>
      <latitude>  35.6564</latitude>
      <longitude>-120.9241</longitude>
      <nfdr_dt>07/05/2020</nfdr_dt>
      <nfdr_tm>13</nfdr_tm>
      <nfdr_type>N</nfdr_type>
      <mp>6</mp>
      <msgc>16Z2A </msgc>
      <one_hr>3.92</one_hr>
      <ten_hr>9.16</ten_hr>
      <hu_hr>12</hu_hr>
      <th_hr>15</th_hr>
      <xh_hr>-100</xh_hr>
      <ic>48.9</ic>
      <kbdi>456</kbdi>
      <sc>9</sc>
      <ec>104.5</ec>
      <bi>70.2</bi>
      <lr>0</lr>
      <lo>0</lo>
      <hr>0</hr>
      <ho>0</ho>
      <fl>50</fl>
      <hrb>53</hrb>
      <wdy>149</wdy>
      <herb_gsi>0.82</herb_gsi>
      <woody_gsi>0.82</woody_gsi>
   </row>
</nfdrs>
